pyessv/__init__.py
pyessv/archive.py
pyessv/constants.py
pyessv/exceptions.py
pyessv/factory.py
pyessv/factory_for_testing.py
pyessv/governance.py
pyessv/initializer.py
pyessv/io_manager.py
pyessv/loader.py
pyessv/parser.py
pyessv/parser_template.py
pyessv/validation.py
pyessv/accessors/__init__.py
pyessv/accessors/copernicus_cordexp.py
pyessv/accessors/esdoc_cmip6.py
pyessv/accessors/wcrp_cmip6.py
pyessv/cache/__init__.py
pyessv/cache/store.py
pyessv/cache/store_memory.py
pyessv/codecs/__init__.py
pyessv/codecs/dict_codec/__init__.py
pyessv/codecs/dict_codec/decoder.py
pyessv/codecs/dict_codec/encoder.py
pyessv/codecs/json_codec/__init__.py
pyessv/codecs/json_codec/decoder.py
pyessv/codecs/json_codec/encoder.py
pyessv/model/__init__.py
pyessv/model/authority.py
pyessv/model/collection.py
pyessv/model/node.py
pyessv/model/scope.py
pyessv/model/term.py
pyessv/parsers/__init__.py
pyessv/parsers/cmip5_dataset_id.py
pyessv/parsers/cmip6_dataset_id.py
pyessv/parsers/cordex_dataset_id.py
pyessv/parsers/input4mips_dataset_id.py
pyessv/utils/__init__.py
pyessv/utils/compat.py
pyessv/utils/compat2_datetime.py
pyessv/utils/convert.py
pyessv/utils/formatter.py
pyessv/utils/logger.py
pyessv/utils/validation.py
tests/__init__.py
tests/test_cache.py
tests/test_codecs.py
tests/test_factory.py
tests/test_governance.py
tests/test_interface.py
tests/test_io_manager.py
tests/test_model.py
tests/test_parse_identifiers.py
tests/test_parser_name.py
tests/test_parser_template.py
tests/test_validation_01.py
tests/test_validation_02.py
tests/utils.py
tests/utils_assert.py
tests/utils_factory.py
tests/utils_model.py
pyessv-0.9.1.0.dist-info/LICENSE
pyessv-0.9.1.0.dist-info/METADATA
pyessv-0.9.1.0.dist-info/WHEEL
pyessv-0.9.1.0.dist-info/top_level.txt
pyessv-0.9.1.0.dist-info/RECORD
