Metadata-Version: 2.1
Name: pyessv
Version: 0.9.1.0
Summary: pyessv is a python library for managing earth system standard vocabularies.
Home-page: https://github.com/ES-DOC/pyessv
Author: Mark A. Greenslade
Author-email: momipsl@ipsl.jussieu.fr
License: GPL/CeCILL-2.1
Classifier: Development Status :: 4 - Beta
Classifier: Intended Audience :: Developers
Classifier: Natural Language :: English
Classifier: License :: OSI Approved :: GNU General Public License (GPL)
Classifier: License :: OSI Approved :: CEA CNRS Inria Logiciel Libre License, version 2.1 (CeCILL-2.1)
Classifier: Operating System :: OS Independent
Classifier: Programming Language :: Python
Classifier: Programming Language :: Python :: 2
Classifier: Programming Language :: Python :: 2.7
Classifier: Programming Language :: Python :: 3
Classifier: Topic :: Software Development :: Libraries :: Python Modules
License-File: LICENSE
Requires-Dist: pytest
Requires-Dist: tox
